mcp_image_seededit/__init__.py
mcp_image_seededit/main.py
mcp_image_seededit/.claude/settings.local.json
mcp_image_seededit-0.5.0.dist-info/METADATA
mcp_image_seededit-0.5.0.dist-info/WHEEL
mcp_image_seededit-0.5.0.dist-info/entry_points.txt
mcp_image_seededit-0.5.0.dist-info/licenses/LICENSE
mcp_image_seededit-0.5.0.dist-info/RECORD
