Metadata-Version: 2.4
Name: mcp-image-seededit
Version: 0.5.0
Summary: MCP服务器，提供火山引擎SeedEdit 3.0图像指令编辑和人物写真生成功能
Project-URL: Homepage, https://github.com/yourusername/mcp-image-seededit
Project-URL: Repository, https://github.com/yourusername/mcp-image-seededit
Project-URL: Documentation, https://github.com/yourusername/mcp-image-seededit#readme
Project-URL: Bug Tracker, https://github.com/yourusername/mcp-image-seededit/issues
Author-email: fengjinchao <your-email@example.com>
Maintainer-email: fengjinchao <your-email@example.com>
License-Expression: MIT
License-File: LICENSE
Keywords: ai,image-editing,mcp,model-context-protocol,portrait-generation,seededit,volcengine
Classifier: Development Status :: 4 - Beta
Classifier: Intended Audience :: Developers
Classifier: License :: OSI Approved :: MIT License
Classifier: Programming Language :: Python :: 3
Classifier: Programming Language :: Python :: 3.10
Classifier: Programming Language :: Python :: 3.11
Classifier: Programming Language :: Python :: 3.12
Classifier: Topic :: Multimedia :: Graphics :: Graphics Conversion
Classifier: Topic :: Scientific/Engineering :: Artificial Intelligence
Classifier: Topic :: Software Development :: Libraries :: Python Modules
Requires-Python: >=3.10
Requires-Dist: httpx[socks]>=0.28.1
Requires-Dist: mcp[cli]>=1.12.0
Requires-Dist: pillow>=9.0.0
Requires-Dist: volcengine>=1.0.0
Provides-Extra: dev
Requires-Dist: black>=23.0.0; extra == 'dev'
Requires-Dist: flake8>=6.0.0; extra == 'dev'
Requires-Dist: isort>=5.0.0; extra == 'dev'
Requires-Dist: mypy>=1.0.0; extra == 'dev'
Requires-Dist: pytest-asyncio>=0.21.0; extra == 'dev'
Requires-Dist: pytest>=7.0.0; extra == 'dev'
